pae/smtp/__init__.py
pae/smtp/checks.py
pae/smtp/client.py
pae/smtp/default_settings.py
pae/smtp/factory.py
pyApp_SMTP-1.0b1.dist-info/METADATA
pyApp_SMTP-1.0b1.dist-info/WHEEL
pyApp_SMTP-1.0b1.dist-info/top_level.txt
pyApp_SMTP-1.0b1.dist-info/RECORD
