Metadata-Version: 2.1
Name: pyApp-SMTP
Version: 1.0b1
Summary: SMTP Extension for pyApp
Home-page: https://github.com/pyapp-org
Author: Tim Savage
Author-email: tim@savage.company
License: BSD
Keywords: application,framework,pyApp,smtp
Platform: any
Classifier: Development Status :: 4 - Beta
Classifier: Intended Audience :: Developers
Classifier: License :: OSI Approved :: BSD License
Classifier: Operating System :: OS Independent
Classifier: Topic :: Software Development :: Libraries :: Python Modules
Classifier: Topic :: Software Development :: Libraries :: Application Frameworks
Classifier: Programming Language :: Python :: 3
Classifier: Programming Language :: Python :: 3.6
Classifier: Programming Language :: Python :: 3.7
Classifier: Programming Language :: Python :: Implementation :: CPython
Classifier: Programming Language :: Python :: Implementation :: PyPy
Requires-Python: >= 3.6
Requires-Dist: pyapp (>=4.0b1)
Provides-Extra: dev
Requires-Dist: black ; extra == 'dev'
